COPYING.LESSER.txt
COPYING.txt
MANIFEST.in
README
setup.py
snakewatch/__init__.py
snakewatch/config.py
snakewatch/main.py
snakewatch/util.py
snakewatch.egg-info/PKG-INFO
snakewatch.egg-info/SOURCES.txt
snakewatch.egg-info/dependency_links.txt
snakewatch.egg-info/entry_points.txt
snakewatch.egg-info/requires.txt
snakewatch.egg-info/top_level.txt
snakewatch/action/Exit.py
snakewatch/action/Ignore.py
snakewatch/action/Print.py
snakewatch/action/Write.py
snakewatch/action/_Action.py
snakewatch/action/_ConfirmAction.py
snakewatch/action/__init__.py
snakewatch/input/File.py
snakewatch/input/STD.py
snakewatch/input/_Input.py
snakewatch/input/__init__.py
snakewatch/mode/Console.py
snakewatch/mode/__init__.py