Metadata-Version: 1.1
Name: snakewatch
Version: 1.0.0
Summary: snakewatch v1.0.0
Home-page: https://github.com/asoc/snakewatch
Author: Alex Honeywell
Author-email: alex.honeywell@gmail.com
License: LGPL
Keywords: log,tail
Platform: UNKNOWN
Classifier: Development Status :: 5 - Production/Stable
Classifier: Environment :: Console
Classifier: Intended Audience :: Developers
Classifier: Intended Audience :: System Administrators
Classifier: License :: OSI Approved :: GNU Library or Lesser General Public License (LGPL)
Classifier: Operating System :: OS Independent
Classifier: Programming Language :: Python
Classifier: Topic :: System :: Logging
